tree_py/__init__.py
tree_py/core.py
tree_py/display.py
tree_py/main.py
tree_py_shiso-0.2.0.dist-info/METADATA
tree_py_shiso-0.2.0.dist-info/WHEEL
tree_py_shiso-0.2.0.dist-info/entry_points.txt
tree_py_shiso-0.2.0.dist-info/RECORD
