Metadata-Version: 2.4
Name: tree-py-shiso
Version: 0.2.0
Summary: A Python implementation of the tree command for Windows
Project-URL: Repository, https://github.com/tinnci/tree-py
Author-email: shiso <shisoratsu@icloud.com>
Classifier: License :: OSI Approved :: MIT License
Classifier: Operating System :: Microsoft :: Windows
Classifier: Programming Language :: Python :: 3
Requires-Python: >=3.8
